



















    
    

	{
	"title": "Web",
	"app_name": "web",
	"chat_appId": "web",
	"icon": "file:///usr/palm/applications/com.palm.app.browser/icon.png",
	"sort_by":null,
	"json_result" : "Success",
	"items": [
   

			{
				"text" : "Websites öffnen",
    			"url" : 
				
    				"http://help.palm.com:80/de-de/c090-01/d500-01/article/39603.html",
    			
    		"link_number" : "1: 1.0"
    		 
    		    },       		
    

			{
				"text" : "Website suchen",
    			"url" : 
				
    				"http://help.palm.com:80/de-de/c090-01/d500-01/article/39609.html",
    			
    		"link_number" : "2: 2.0"
    		 
    		    },       		
    

			{
				"text" : "Auf Webseiten navigieren",
    			"url" : 
				
    				"http://help.palm.com:80/de-de/c090-01/d500-01/article/39614.html",
    			
    		"link_number" : "3: 3.0"
    		 
    		    },       		
    

			{
				"text" : "Ein neues Browserfenster öffnen",
    			"url" : 
				
    				"http://help.palm.com:80/de-de/c090-01/d500-01/article/39618.html",
    			
    		"link_number" : "4: 4.0"
    		 
    		    },       		
    

			{
				"text" : "Webseite drucken",
    			"url" : 
				
    				"http://help.palm.com:80/de-de/c090-01/d500-01/article/39621.html",
    			
    		"link_number" : "5: 5.0"
    		 
    		    },       		
    

			{
				"text" : "Flash-Inhalte verwenden",
    			"url" : 
				
    				"http://help.palm.com:80/de-de/c090-01/d500-01/article/39627.html",
    			
    		"link_number" : "6: 6.0"
    		 
    		    },       		
    

			{
				"text" : "Webseiten zum Startbildschirm hinzufügen",
    			"url" : 
				
    				"http://help.palm.com:80/de-de/c090-01/d500-01/article/39632.html",
    			
    		"link_number" : "7: 7.0"
    		 
    		    },       		
    

			{
				"text" : "Favoriten erstellen",
    			"url" : 
				
    				"http://help.palm.com:80/de-de/c090-01/d500-01/article/41399.html",
    			
    		"link_number" : "8: 8.0"
    		 
    		    },       		
    

			{
				"text" : "Favoritenseiten öffnen",
    			"url" : 
				
    				"http://help.palm.com:80/de-de/c090-01/d500-01/article/41404.html",
    			
    		"link_number" : "9: 9.0"
    		 
    		    },       		
    

			{
				"text" : "Favoriten bearbeiten oder löschen",
    			"url" : 
				
    				"http://help.palm.com:80/de-de/c090-01/d500-01/article/39611.html",
    			
    		"link_number" : "10: 10.0"
    		 
    		    },       		
    

			{
				"text" : "Zu zuvor besuchten Webseiten zurückkehren",
    			"url" : 
				
    				"http://help.palm.com:80/de-de/c090-01/d500-01/article/41410.html",
    			
    		"link_number" : "11: 11.0"
    		 
    		    },       		
    

			{
				"text" : "Verknüpfungen auf Webseiten verwenden",
    			"url" : 
				
    				"http://help.palm.com:80/de-de/c090-01/d500-01/article/41414.html",
    			
    		"link_number" : "12: 12.0"
    		 
    		    },       		
    

			{
				"text" : "Auf einer Webseite mit Bildern arbeiten",
    			"url" : 
				
    				"http://help.palm.com:80/de-de/c090-01/d500-01/article/41418.html",
    			
    		"link_number" : "13: 13.0"
    		 
    		    },       		
    

			{
				"text" : "Dateien vom Web herunterladen",
    			"url" : 
				
    				"http://help.palm.com:80/de-de/c090-01/d500-01/article/41420.html",
    			
    		"link_number" : "14: 14.0"
    		 
    		    },       		
    

			{
				"text" : "Websuchmaschine hinzufügen",
    			"url" : 
				
    				"http://help.palm.com:80/de-de/c090-01/d500-01/article/41424.html",
    			
    		"link_number" : "15: 15.0"
    		 
    		    },       		
    

			{
				"text" : "Einstellungen des Internetbrowsers anpassen",
    			"url" : 
				
    				"http://help.palm.com:80/de-de/c090-01/d500-01/article/41427.html",
    			
    		"link_number" : "16: 16.0"
    		 
    		    }       		
    
     ]
    }
  	
 

