



















    
    

	{
	"title": "! Conceptos básicos",
	"app_name": "basics",
	"chat_appId": "basics",
	"icon": "file:///usr/palm/applications/com.palm.app.help/images/basics.png",
	"sort_by":null,
	"json_result" : "Success",
	"items": [
   

			{
				"text" : "Funcionamiento del smartphone",
    			"url" : 
				
    			"http://help.palm.com:80/es-es/c027-01/d400-01/toc/43488/index.html",
    			
    		"link_number" : "1: 1.0"
    		 
    		    },       		
    

			{
				"text" : "Encendido/apagado del smartphone",
    			"url" : 
				
    			"http://help.palm.com:80/es-es/c027-01/d400-01/toc/43489/index.html",
    			
    		"link_number" : "2: 2.0"
    		 
    		    },       		
    

			{
				"text" : "Desplazamiento por el smartphone",
    			"url" : 
				
    			"http://help.palm.com:80/es-es/c027-01/d400-01/toc/43493/index.html",
    			
    		"link_number" : "3: 3.0"
    		 
    		    },       		
    

			{
				"text" : "Apertura de aplicaciones",
    			"url" : 
				
    			"http://help.palm.com:80/es-es/c027-01/d400-01/toc/43495/index.html",
    			
    		"link_number" : "4: 4.0"
    		 
    		    },       		
    

			{
				"text" : "Administración de aplicaciones",
    			"url" : 
				
    			"http://help.palm.com:80/es-es/c027-01/d400-01/toc/43499/index.html",
    			
    		"link_number" : "5: 5.0"
    		 
    		    },       		
    

			{
				"text" : "Introducción de información",
    			"url" : 
				
    			"http://help.palm.com:80/es-es/c027-01/d400-01/toc/43494/index.html",
    			
    		"link_number" : "6: 6.0"
    		 
    		    },       		
    

			{
				"text" : "Uso de los menús",
    			"url" : 
				
    			"http://help.palm.com:80/es-es/c027-01/d400-01/toc/43500/index.html",
    			
    		"link_number" : "7: 7.0"
    		 
    		    },       		
    

			{
				"text" : "Sincronización de datos personales y copia de archivos entre el smartphone y el ordenador",
    			"url" : 
				
    			"http://help.palm.com:80/es-es/c027-01/d400-01/toc/43504/index.html",
    			
    		"link_number" : "8: 8.0"
    		 
    		    },       		
    

			{
				"text" : "Uso del asistente de transferencia de datos (ATD)",
    			"url" : 
				
    				"http://help.palm.com:80/es-es/c027-01/d400-01/article/44289.html",
    			
    		"link_number" : "9: 9.0"
    		 
    		    },       		
    

			{
				"text" : "6Ts: Seis técnicas para que tu smartphone vuelva a funcionar",
    			"url" : 
				
    			"http://help.palm.com:80/es-es/c027-01/d400-01/toc/43506/index.html",
    			
    		"link_number" : "10: 10.0"
    		 
    		    },       		
    

			{
				"text" : "Obtención de ayuda en la Ayuda",
    			"url" : 
				
    			"http://help.palm.com:80/es-es/c027-01/d400-01/toc/43508/index.html",
    			
    		"link_number" : "11: 11.0"
    		 
    		    },       		
    

			{
				"text" : "Más información",
    			"url" : 
				
    			"http://help.palm.com:80/es-es/c027-01/d400-01/toc/43510/index.html",
    			
    		"link_number" : "12: 12.0"
    		 
    		    }       		
    
     ]
    }
  	
 

