



















    
    

	{
	"title": "Work with slideshows and display options in a Microsoft PowerPoint® presentation",
	"app_name": "quickoffice",
	"chat_appId": "quickoffice",
	"icon": "http://help.palm.com/images/app_icons/quickoffice.png",
	"sort_by":null,
	"json_result" : "Success",
	"items": [
   

			{
				"text" : "Switch between slides in a PowerPoint&reg; slideshow",
    			"url" : 
				
    				"http://help.palm.com:80/en-ie/c027-01/d400-01/article/18327.html",
    			
    		"link_number" : "1: 1.0"
    		 
    		    },       		
    

			{
				"text" : "Zoom in and pan on a slide",
    			"url" : 
				
    				"http://help.palm.com:80/en-ie/c027-01/d400-01/article/18341.html",
    			
    		"link_number" : "2: 2.0"
    		 
    		    }       		
    
     ]
    }
  	
 

